actor/__init__.py
actor/__main__.py
actor/cli.py
actor/tests/__init__.py
actor-0.0.0.dist-info/AUTHORS.rst
actor-0.0.0.dist-info/LICENSE
actor-0.0.0.dist-info/METADATA
actor-0.0.0.dist-info/WHEEL
actor-0.0.0.dist-info/entry_points.txt
actor-0.0.0.dist-info/top_level.txt
actor-0.0.0.dist-info/RECORD
