Metadata-Version: 2.1
Name: actor
Version: 0.0.0
Summary: A simple actor framework with dynamic parallelism
Home-page: https://github.com/yasserfarouk/actor
Author: Yasser Mohammad
Author-email: yasserfarouk@gmail.com
License: LGPL-2.1-or-later
Project-URL: Documentation, https://actor.readthedocs.io/
Project-URL: Changelog, https://actor.readthedocs.io/en/latest/changelog.html
Project-URL: Issue Tracker, https://github.com/yasserfarouk/actor/issues
Platform: UNKNOWN
Classifier: License :: OSI Approved :: GNU General Public License v2 or later (GPLv2+)
Classifier: Programming Language :: Python :: 3
Classifier: Programming Language :: Python :: 3.6
Classifier: Programming Language :: Python :: 3.7
Classifier: Programming Language :: Python :: 3.8
Requires-Python: >=2.7, !=3.0.*, !=3.1.*, !=3.2.*, !=3.3.*, !=3.4.*
Requires-Dist: click
